gnssir/__init__.py
gnssir/cli.py
gnssir/elv_interp.py
gnssir/gpt_1wA.pickle
gnssir/helper.py
gnssir/make_gpt.py
gnssir/plot.py
gnssir/processing.py
gnssir/tropd.py
gnssir_rt-2.0.0.dist-info/licenses/LICENSE
gnssir_rt-2.0.0.dist-info/METADATA
gnssir_rt-2.0.0.dist-info/WHEEL
gnssir_rt-2.0.0.dist-info/entry_points.txt
gnssir_rt-2.0.0.dist-info/top_level.txt
gnssir_rt-2.0.0.dist-info/RECORD
