Metadata-Version: 2.4
Name: gnssir-rt
Version: 2.0.0
Summary: Real-time processing tools for GNSS-IR water level monitoring and flood detection
Author-email: David Purnell <davejpurnell@gmail.com>
License: BSD-3-Clause
Project-URL: Homepage, https://github.com/purnelldj/gnssir-rt
Project-URL: Documentation, https://github.com/purnelldj/gnssir-rt#readme
Project-URL: Repository, https://github.com/purnelldj/gnssir-rt.git
Project-URL: Issues, https://github.com/purnelldj/gnssir-rt/issues
Project-URL: Changelog, https://github.com/purnelldj/gnssir-rt/blob/main/CHANGELOG.md
Keywords: gnss,gnss-ir,water-level,flood-monitoring,remote-sensing,interferometry
Classifier: Development Status :: 4 - Beta
Classifier: Intended Audience :: Science/Research
Classifier: License :: OSI Approved :: BSD License
Classifier: Operating System :: OS Independent
Classifier: Programming Language :: Python :: 3
Classifier: Programming Language :: Python :: 3.9
Classifier: Programming Language :: Python :: 3.10
Classifier: Programming Language :: Python :: 3.11
Classifier: Programming Language :: Python :: 3.12
Requires-Python: >=3.9
License-File: LICENSE
Requires-Dist: astropy
Requires-Dist: jsonargparse
Requires-Dist: matplotlib
Requires-Dist: numpy
Requires-Dist: scipy
Requires-Dist: zenodo-get
Provides-Extra: dev
Requires-Dist: ruff; extra == "dev"
Requires-Dist: pre-commit; extra == "dev"
Requires-Dist: pytest; extra == "dev"
Dynamic: license-file
